secd_KTHCLOUD/__init__.py
secd_KTHCLOUD/example.py
secd_KTHCLOUD/secd.py
secd_kthcloud-0.0.5.dist-info/METADATA
secd_kthcloud-0.0.5.dist-info/WHEEL
secd_kthcloud-0.0.5.dist-info/licenses/LICENCE
secd_kthcloud-0.0.5.dist-info/RECORD
